Workbook

Sheet operators
A1: E&P OPERATOR REFERENCE TABLE
A2: operator_id | B2: company_name | C2: ticker | D2: country | E2: primary_basin | F2: commodity_focus | G2: data_status
A3: 1 | B3: Antero Resources | C3: AR | D3: USA | E3: Appalachia (Marcellus / Utica) | F3: Gas-weighted | G3: Complete
A4: 2 | B4: BKV Corporation | C4: BKV | D4: USA | E4: Barnett Shale / Appalachia | F4: Gas-weighted | G4: Complete
A5: 3 | B5: Canadian Natural Resources | C5: CNQ | D5: Canada | E5: Oil Sands / Montney / Pelican Lake | F5: Oil-weighted | G5: Complete
A6: 4 | B6: Cenovus Energy | C6: CVE | D6: Canada | E6: Oil Sands / Deep Basin / Offshore | F6: Oil-weighted | G6: Complete
A7: 5 | B7: Chevron | C7: CVX | D7: USA | E7: Permian / Gulf of Mexico / International | F7: Diversified | G7: Complete
A8: 6 | B8: Chord Energy | C8: CHRD | D8: USA | E8: Williston Basin (Bakken / Three Forks) | F8: Oil-weighted | G8: Complete
A9: 7 | B9: ConocoPhillips | C9: COP | D9: USA | E9: Permian / Eagle Ford / Bakken / Alaska | F9: Diversified | G9: Complete
A10: 8 | B10: Coterra Energy | C10: CTRA | D10: USA | E10: Permian / Marcellus / Anadarko | F10: Diversified | G10: Complete
A11: 9 | B11: Devon Energy | C11: DVN | D11: USA | E11: Delaware Basin / Anadarko / Eagle Ford | F11: Oil-weighted | G11: Complete
A12: 10 | B12: Diamondback Energy | C12: FANG | D12: USA | E12: Permian (Midland + Delaware) | F12: Oil-weighted | G12: Complete
A13: 11 | B13: EOG Resources | C13: EOG | D13: USA | E13: Permian / Eagle Ford / Bakken | F13: Oil-weighted | G13: Complete
A14: 12 | B14: EQT Corporation | C14: EQT | D14: USA | E14: Appalachia (Marcellus / Utica) | F14: Gas-weighted | G14: Complete
... A21: 19 | B21: Permian Resources | C21: PR | D21: USA | E21: Delaware Basin (Permian) | F21: Oil-weighted | G21: Complete

Sheet production
A1: QUARTERLY OIL & GAS PRODUCTION | 2023 Q1 – 2024 Q4
A2: Units: Oil = MBbl/d (thousands of barrels per day) | Gas = MMcf/d (millions of cubic feet per day)
A3: operator_id | B3: company_name | C3: 2023-Q1 Oil | D3: 2023-Q1 Gas | E3: 2023-Q2 Oil | F3: 2023-Q2 Gas | G3: 2023-Q3 Oil | H3: 2023-Q3 Gas | I3: 2023-Q4 Oil | J3: 2023-Q4 Gas | K3: 2024-Q1 Oil | L3: 2024-Q1 Gas | M3: 2024-Q2 Oil | N3: 2024-Q2 Gas | O3: 2024-Q3 Oil | P3: 2024-Q3 Gas | Q3: 2024-Q4 Oil | R3: 2024-Q4 Gas
A4: 1 | B4: Antero Resources | C4: 8.2 | D4: 2133 | E4: 10.7 | F4: 2242 | G4: 10.6 | H4: 2190 | I4: 10.1 | J4: 2214 | K4: 10.3 | L4: 2232 | M4: 11.1 | N4: 2260 | O4: 10.8 | P4: 2244 | Q4: 11 | R4: 2280
A5: 2 | B5: BKV Corporation | D5: 700 | F5: 760 | H5: 845 | J5: 838 | L5: 830 | N5: 794 | P5: 763 | R5: 775
A6: 3 | B6: Canadian Natural Resources | C6: 792 | D6: 1460 | E6: 808 | F6: 1490 | G6: 862 | H6: 1505 | I6: 952 | J6: 1520 | K6: 940 | L6: 1470 | M6: 958 | N6: 1490 | O6: 965 | P6: 1520 | Q6: 980 | R6: 1550
A7: 4 | B7: Cenovus Energy | C7: 528 | D7: 840 | E7: 540 | F7: 832 | G7: 555 | H7: 845 | I7: 663 | J7: 876 | K7: 636 | L7: 844 | M7: 648 | N7: 851 | O7: 631 | P7: 845 | Q7: 671 | R7: 873
A8: 5 | B8: Chevron | C8: 716 | D8: 4308 | E8: 730 | F8: 4242 | G8: 728 | H8: 4368 | I8: 745 | J8: 4326 | K8: 761 | L8: 5052 | M8: 762 | N8: 5028 | O8: 756 | P8: 5022 | Q8: 758 | R8: 5004
A9: 6 | B9: Chord Energy | C9: 174 | D9: 305 | E9: 175 | F9: 310 | G9: 176 | H9: 315 | I9: 177 | J9: 316 | K9: 178 | L9: 320 | M9: 180 | N9: 325 | O9: 182 | P9: 330 | Q9: 185 | R9: 335
A10: 7 | B10: ConocoPhillips | C10: 605 | D10: 1453 | E10: 605 | F10: 1453 | G10: 600 | H10: 1440 | I10: 610 | J10: 1450 | K10: 625 | L10: 1470 | M10: 622 | N10: 1462 | O10: 610 | P10: 1448 | Q10: 660 | R10: 1524
A11: 8 | B11: Coterra Energy | C11: 95 | D11: 2160 | E11: 97 | F11: 2100 | G11: 100 | H11: 2080 | I11: 102 | J11: 2020 | K11: 103 | L11: 2050 | M11: 104 | N11: 2010 | O11: 106 | P11: 2020 | Q11: 109 | R11: 2030
A12: 9 | B12: Devon Energy | C12: 317 | D12: 993 | E12: 309 | F12: 985 | G12: 318 | H12: 987 | I12: 323 | J12: 993 | K12: 335 | L12: 1020 | M12: 335 | N12: 1005 | O12: 332 | P12: 996 | Q12: 324 | R12: 984
A13: 10 | B13: Diamondback Energy | C13: 248 | D13: 820 | E13: 252 | F13: 857 | G13: 267 | H13: 895 | I13: 263 | J13: 870 | K13: 278 | L13: 915 | M13: 284 | N13: 960 | O13: 301 | P13: 1020 | Q13: 320 | R13: 1085
A14: 11 | B14: EOG Resources | C14: 472 | D14: 1371 | E14: 479 | F14: 1410 | G14: 475 | H14: 1400 | I14: 495 | J14: 1430 | K14: 498 | L14: 1440 | M14: 508 | N14: 1460 | O14: 512 | P14: 1475 | Q14: 515 | R14: 1490
A15: 12 | B15: EQT Corporation | D15: 5220 | F15: 5280 | H15: 5250 | J15: 5400 | L15: 5820 | N15: 5760 | P15: 5730 | R15: 5760
A16: 13 | B16: Expand Energy | C16: 15 | D16: 3264 | E16: 14 | F16: 3507 | G16: 12 | H16: 3355 | I16: 11 | J16: 3220 | K16: 12 | L16: 3200 | M16: 12 | N16: 2745 | O16: 13 | P16: 2900 | Q16: 16 | R16: 5826
A17: 14 | B17: ExxonMobil | C17: 1524 | D17: 4260 | E17: 1494 | F17: 4080 | G17: 1504 | H17: 4116 | I17: 1514 | J17: 4176 | K17: 1563 | L17: 5148 | M17: 1596 | N17: 5196 | O17: 1599 | P17: 5208 | Q17: 1626 | R17: 5220
A18: 15 | B18: Imperial Oil | C18: 350 | E18: 355 | G18: 360 | I18: 380 | K18: 392 | M18: 385 | O18: 398 | Q18: 408
A19: 16 | B19: Matador Resources | C19: 52 | D19: 266 | E19: 76 | F19: 326 | G19: 78 | H19: 345 | I19: 80 | J19: 352 | K19: 83 | L19: 363 | M19: 88 | N19: 378 | O19: 92 | P19: 392 | Q19: 96 | R19: 405
A20: 17 | B20: Occidental Petroleum | C20: 484 | D20: 2298 | E20: 479 | F20: 2262 | G20: 489 | H20: 2298 | I20: 496 | J20: 2304 | K20: 531 | L20: 2412 | M20: 544 | N20: 2478 | O20: 564 | P20: 2556 | Q20: 575 | R20: 2586
A21: 18 | B21: Suncor Energy | C21: 626 | D21: 405 | E21: 656 | F21: 430 | G21: 683 | H21: 450 | I21: 725 | J21: 458 | K21: 736 | L21: 430 | M21: 754 | N21: 440 | O21: 760 | P21: 448 | Q21: 768 | R21: 452
A22: 19 | B22: Permian Resources | C22: 102 | D22: 310 | E22: 110 | F22: 330 | G22: 130 | H22: 387 | I22: 148 | J22: 443 | K22: 153 | L22: 455 | M22: 170 | N22: 502 | O22: 178 | P22: 525 | Q22: 182 | R22: 535

Sheet financials
A1: QUARTERLY FINANCIALS | CAPEX & FREE CASH FLOW | 2023 Q1 – 2024 Q4
A2: Units: Capex = $MM (millions USD) | FCF = $MM (millions USD) | Canadian companies reported in CAD$MM, converted at approximate period FX
A3: operator_id | B3: company_name | C3: 2023-Q1 Capex | D3: 2023-Q1 FCF | E3: 2023-Q2 Capex | F3: 2023-Q2 FCF | G3: 2023-Q3 Capex | H3: 2023-Q3 FCF | I3: 2023-Q4 Capex | J3: 2023-Q4 FCF | K3: 2024-Q1 Capex | L3: 2024-Q1 FCF | M3: 2024-Q2 Capex | N3: 2024-Q2 FCF | O3: 2024-Q3 Capex | P3: 2024-Q3 FCF | Q3: 2024-Q4 Capex | R3: 2024-Q4 FCF
A4: 1 | B4: Antero Resources | C4: 218 | D4: 81 | E4: 196 | F4: 105 | G4: 186 | H4: 98 | I4: 188 | J4: 110 | K4: 166 | L4: 62 | M4: 148 | N4: 159 | O4: 148 | P4: 100 | Q4: 155 | R4: 159
A5: 2 | B5: BKV Corporation | C5: 115 | D5: -11 | E5: 120 | F5: -9 | G5: 98 | H5: -11 | I5: 90 | J5: 12 | K5: 80 | L5: 15 | M5: 72 | N5: 18 | O5: 74 | P5: 20 | Q5: 75 | R5: 22
A6: 3 | B6: Canadian Natural Resources | C6: 1100 | D6: 1350 | E6: 1200 | F6: 1480 | G6: 1150 | H6: 1520 | I6: 1050 | J6: 1620 | K6: 1080 | L6: 1500 | M6: 1200 | N6: 1600 | O6: 1150 | P6: 1700 | Q6: 1080 | R6: 1800
A7: 4 | B7: Cenovus Energy | C7: 900 | D7: 780 | E7: 920 | F7: 850 | G7: 870 | H7: 920 | I7: 860 | J7: 950 | K7: 880 | L7: 830 | M7: 900 | N7: 870 | O7: 880 | P7: 910 | Q7: 860 | R7: 920
A8: 5 | B8: Chevron | C8: 3800 | D8: 3100 | E8: 3900 | F8: 3200 | G8: 4200 | H8: 3500 | I8: 4100 | J8: 3800 | K8: 3600 | L8: 2900 | M8: 3700 | N8: 3100 | O8: 4000 | P8: 3300 | Q8: 3800 | R8: 3600
A9: 6 | B9: Chord Energy | C9: 430 | D9: 210 | E9: 440 | F9: 230 | G9: 420 | H9: 250 | I9: 400 | J9: 280 | K9: 410 | L9: 290 | M9: 420 | N9: 310 | O9: 400 | P9: 330 | Q9: 390 | R9: 350
A10: 7 | B10: ConocoPhillips | C10: 2700 | D10: 2900 | E10: 2500 | F10: 3100 | G10: 2900 | H10: 2800 | I10: 2700 | J10: 3000 | K10: 3800 | L10: 2500 | M10: 3600 | N10: 2700 | O10: 3800 | P10: 2600 | Q10: 3900 | R10: 2800
A11: 8 | B11: Coterra Energy | C11: 510 | D11: 310 | E11: 480 | F11: 370 | G11: 430 | H11: 350 | I11: 420 | J11: 400 | K11: 390 | L11: 320 | M11: 380 | N11: 350 | O11: 370 | P11: 360 | Q11: 380 | R11: 400
A12: 9 | B12: Devon Energy | C12: 900 | D12: 720 | E12: 830 | F12: 780 | G12: 850 | H12: 810 | I12: 820 | J12: 850 | K12: 880 | L12: 730 | M12: 850 | N12: 760 | O12: 820 | P12: 780 | Q12: 800 | R12: 820
A13: 10 | B13: Diamondback Energy | C13: 670 | D13: 590 | E13: 750 | F13: 640 | G13: 760 | H13: 700 | I13: 720 | J13: 750 | K13: 780 | L13: 700 | M13: 850 | N13: 810 | O13: 850 | P13: 870 | Q13: 890 | R13: 950
A14: 11 | B14: EOG Resources | C14: 1500 | D14: 1800 | E14: 1490 | F14: 1700 | G14: 1520 | H14: 1600 | I14: 1480 | J14: 1800 | K14: 1520 | L14: 1750 | M14: 1550 | N14: 1900 | O14: 1530 | P14: 1850 | Q14: 1510 | R14: 1950
A15: 12 | B15: EQT Corporation | C15: 450 | D15: 530 | E15: 420 | F15: 610 | G15: 390 | H15: 680 | I15: 380 | J15: 720 | K15: 1200 | L15: 480 | M15: 850 | N15: 620 | O15: 780 | P15: 700 | Q15: 760 | R15: 780
... A22: 19 | B22: Permian Resources | C22: 440 | D22: 75 | E22: 470 | F22: 100 | G22: 470 | H22: 215 | I22: 450 | J22: 270 | K22: 470 | L22: 230 | M22: 520 | N22: 330 | O22: 510 | P22: 360 | Q22: 490 | R22: 400

Sheet calculations
A1: ANALYTICAL CALCULATIONS | Annual Averages · YoY Growth · CAGR · Capex Efficiency
A2: NOTE: Annual oil/gas = simple average of 4 quarters (MBbl/d / MMcf/d) | FCF/Capex = annual sum ($MM)
A3: operator_id | B3: company_name | C3: 2023 Avg Oil (MBbl/d) | D3: 2023 Avg Gas (MMcf/d) | E3: 2024 Avg Oil (MBbl/d) | F3: 2024 Avg Gas (MMcf/d) | G3: YoY Oil Growth % | H3: YoY Gas Growth % | I3: 2023 Capex ($MM) | J3: 2023 FCF ($MM) | K3: 2024 Capex ($MM) | L3: 2024 FCF ($MM) | M3: Capex Eff 2023 (BOE/$MM Capex) | N3: Capex Eff 2024 (BOE/$MM Capex) | O3: FCF Growth 2023→2024 % | P3: FCF Margin 2024 %
A4: 1 | B4: Antero Resources | C4: =IFERROR(AVERAGE(production!C4,production!E4,production!G4,production!I4),"N/A") -> 9.9 | D4: =IFERROR(AVERAGE(production!D4,production!F4,production!H4,production!J4),"N/A") -> 2194.75 | E4: =IFERROR(AVERAGE(production!K4,production!M4,production!O4,production!Q4),"N/A") -> 10.8 | F4: =IFERROR(AVERAGE(production!L4,production!N4,production!P4,production!R4),"N/A") -> 2254 | G4: =IFERROR(IF(AND(ISNUMBER(C4),ISNUMBER(E4)),(E4-C4)/C4,"N/A"),"N/A") -> 0.090909091 | H4: =IFERROR(IF(AND(ISNUMBER(D4),ISNUMBER(F4)),(F4-D4)/D4,"N/A"),"N/A") -> 0.026996241 | I4: =IFERROR(SUM(financials!C4,financials!E4,financials!G4,financials!I4),"N/A") -> 788 | J4: =IFERROR(SUM(financials!D4,financials!F4,financials!H4,financials!J4),"N/A") -> 394 | K4: =IFERROR(SUM(financials!K4,financials!M4,financials!O4,financials!Q4),"N/A") -> 617 | L4: =IFERROR(SUM(financials!L4,financials!N4,financials!P4,financials!R4),"N/A") -> 480 | M4: =IFERROR(IF(AND(ISNUMBER(C4),ISNUMBER(D4),I4>0),((C4+D4/6)*365)/I4,"N/A"),"N/A") -> 174.01962 | N4: =IFERROR(IF(AND(ISNUMBER(E4),ISNUMBER(F4),K4>0),((E4+F4/6)*365)/K4,"N/A"),"N/A") -> 228.62291 | O4: =IFERROR(IF(AND(ISNUMBER(J4),ISNUMBER(L4),J4<>0),(L4-J4)/ABS(J4),"N/A"),"N/A") -> 0.21827411 | P4: =IFERROR(IF(AND(ISNUMBER(L4),ISNUMBER(K4),K4<>0),L4/K4,"N/A"),"N/A") -> 0.77795786
A5: 2 | B5: BKV Corporation | C5: =IFERROR(AVERAGE(production!C5,production!E5,production!G5,production!I5),"N/A") -> N/A | D5: =IFERROR(AVERAGE(production!D5,production!F5,production!H5,production!J5),"N/A") -> 785.75 | E5: =IFERROR(AVERAGE(production!K5,production!M5,production!O5,production!Q5),"N/A") -> N/A | F5: =IFERROR(AVERAGE(production!L5,production!N5,production!P5,production!R5),"N/A") -> 790.5 | G5: =IFERROR(IF(AND(ISNUMBER(C5),ISNUMBER(E5)),(E5-C5)/C5,"N/A"),"N/A") -> N/A | H5: =IFERROR(IF(AND(ISNUMBER(D5),ISNUMBER(F5)),(F5-D5)/D5,"N/A"),"N/A") -> 0.0060451798 | I5: =IFERROR(SUM(financials!C5,financials!E5,financials!G5,financials!I5),"N/A") -> 423 | J5: =IFERROR(SUM(financials!D5,financials!F5,financials!H5,financials!J5),"N/A") -> -19 | K5: =IFERROR(SUM(financials!K5,financials!M5,financials!O5,financials!Q5),"N/A") -> 301 | L5: =IFERROR(SUM(financials!L5,financials!N5,financials!P5,financials!R5),"N/A") -> 75 | M5: =IFERROR(IF(AND(ISNUMBER(C5),ISNUMBER(D5),I5>0),((C5+D5/6)*365)/I5,"N/A"),"N/A") -> N/A | N5: =IFERROR(IF(AND(ISNUMBER(E5),ISNUMBER(F5),K5>0),((E5+F5/6)*365)/K5,"N/A"),"N/A") -> N/A | O5: =IFERROR(IF(AND(ISNUMBER(J5),ISNUMBER(L5),J5<>0),(L5-J5)/ABS(J5),"N/A"),"N/A") -> 4.9473684 | P5: =IFERROR(IF(AND(ISNUMBER(L5),ISNUMBER(K5),K5<>0),L5/K5,"N/A"),"N/A") -> 0.24916944
A6: 3 | B6: Canadian Natural Resources | C6: =IFERROR(AVERAGE(production!C6,production!E6,production!G6,production!I6),"N/A") -> 853.5 | D6: =IFERROR(AVERAGE(production!D6,production!F6,production!H6,production!J6),"N/A") -> 1493.75 | E6: =IFERROR(AVERAGE(production!K6,production!M6,production!O6,production!Q6),"N/A") -> 960.75 | F6: =IFERROR(AVERAGE(production!L6,production!N6,production!P6,production!R6),"N/A") -> 1507.5 | G6: =IFERROR(IF(AND(ISNUMBER(C6),ISNUMBER(E6)),(E6-C6)/C6,"N/A"),"N/A") -> 0.12565905 | H6: =IFERROR(IF(AND(ISNUMBER(D6),ISNUMBER(F6)),(F6-D6)/D6,"N/A"),"N/A") -> 0.0092050209 | I6: =IFERROR(SUM(financials!C6,financials!E6,financials!G6,financials!I6),"N/A") -> 4500 | J6: =IFERROR(SUM(financials!D6,financials!F6,financials!H6,financials!J6),"N/A") -> 5970 | K6: =IFERROR(SUM(financials!K6,financials!M6,financials!O6,financials!Q6),"N/A") -> 4510 | L6: =IFERROR(SUM(financials!L6,financials!N6,financials!P6,financials!R6),"N/A") -> 6600 | M6: =IFERROR(IF(AND(ISNUMBER(C6),ISNUMBER(D6),I6>0),((C6+D6/6)*365)/I6,"N/A"),"N/A") -> 89.42162 | N6: =IFERROR(IF(AND(ISNUMBER(E6),ISNUMBER(F6),K6>0),((E6+F6/6)*365)/K6,"N/A"),"N/A") -> 98.088692 | O6: =IFERROR(IF(AND(ISNUMBER(J6),ISNUMBER(L6),J6<>0),(L6-J6)/ABS(J6),"N/A"),"N/A") -> 0.10552764 | P6: =IFERROR(IF(AND(ISNUMBER(L6),ISNUMBER(K6),K6<>0),L6/K6,"N/A"),"N/A") -> 1.4634146
A7: 4 | B7: Cenovus Energy | C7: =IFERROR(AVERAGE(production!C7,production!E7,production!G7,production!I7),"N/A") -> 571.5 | D7: =IFERROR(AVERAGE(production!D7,production!F7,production!H7,production!J7),"N/A") -> 848.25 | E7: =IFERROR(AVERAGE(production!K7,production!M7,production!O7,production!Q7),"N/A") -> 646.5 | F7: =IFERROR(AVERAGE(production!L7,production!N7,production!P7,production!R7),"N/A") -> 853.25 | G7: =IFERROR(IF(AND(ISNUMBER(C7),ISNUMBER(E7)),(E7-C7)/C7,"N/A"),"N/A") -> 0.1312336 | H7: =IFERROR(IF(AND(ISNUMBER(D7),ISNUMBER(F7)),(F7-D7)/D7,"N/A"),"N/A") -> 0.0058944887 | I7: =IFERROR(SUM(financials!C7,financials!E7,financials!G7,financials!I7),"N/A") -> 3550 | J7: =IFERROR(SUM(financials!D7,financials!F7,financials!H7,financials!J7),"N/A") -> 3500 | K7: =IFERROR(SUM(financials!K7,financials!M7,financials!O7,financials!Q7),"N/A") -> 3520 | L7: =IFERROR(SUM(financials!L7,financials!N7,financials!P7,financials!R7),"N/A") -> 3530 | M7: =IFERROR(IF(AND(ISNUMBER(C7),ISNUMBER(D7),I7>0),((C7+D7/6)*365)/I7,"N/A"),"N/A") -> 73.295599 | N7: =IFERROR(IF(AND(ISNUMBER(E7),ISNUMBER(F7),K7>0),((E7+F7/6)*365)/K7,"N/A"),"N/A") -> 81.783677 | O7: =IFERROR(IF(AND(ISNUMBER(J7),ISNUMBER(L7),J7<>0),(L7-J7)/ABS(J7),"N/A"),"N/A") -> 0.0085714286 | P7: =IFERROR(IF(AND(ISNUMBER(L7),ISNUMBER(K7),K7<>0),L7/K7,"N/A"),"N/A") -> 1.0028409
A8: 5 | B8: Chevron | C8: =IFERROR(AVERAGE(production!C8,production!E8,production!G8,production!I8),"N/A") -> 729.75 | D8: =IFERROR(AVERAGE(production!D8,production!F8,production!H8,production!J8),"N/A") -> 4311 | E8: =IFERROR(AVERAGE(production!K8,production!M8,production!O8,production!Q8),"N/A") -> 759.25 | F8: =IFERROR(AVERAGE(production!L8,production!N8,production!P8,production!R8),"N/A") -> 5026.5 | G8: =IFERROR(IF(AND(ISNUMBER(C8),ISNUMBER(E8)),(E8-C8)/C8,"N/A"),"N/A") -> 0.040424803 | H8: =IFERROR(IF(AND(ISNUMBER(D8),ISNUMBER(F8)),(F8-D8)/D8,"N/A"),"N/A") -> 0.16597077 | I8: =IFERROR(SUM(financials!C8,financials!E8,financials!G8,financials!I8),"N/A") -> 16000 | J8: =IFERROR(SUM(financials!D8,financials!F8,financials!H8,financials!J8),"N/A") -> 13600 | K8: =IFERROR(SUM(financials!K8,financials!M8,financials!O8,financials!Q8),"N/A") -> 15100 | L8: =IFERROR(SUM(financials!L8,financials!N8,financials!P8,financials!R8),"N/A") -> 12900 | M8: =IFERROR(IF(AND(ISNUMBER(C8),ISNUMBER(D8),I8>0),((C8+D8/6)*365)/I8,"N/A"),"N/A") -> 33.038203 | N8: =IFERROR(IF(AND(ISNUMBER(E8),ISNUMBER(F8),K8>0),((E8+F8/6)*365)/K8,"N/A"),"N/A") -> 38.60298 | O8: =IFERROR(IF(AND(ISNUMBER(J8),ISNUMBER(L8),J8<>0),(L8-J8)/ABS(J8),"N/A"),"N/A") -> -0.051470588 | P8: =IFERROR(IF(AND(ISNUMBER(L8),ISNUMBER(K8),K8<>0),L8/K8,"N/A"),"N/A") -> 0.85430464
A9: 6 | B9: Chord Energy | C9: =IFERROR(AVERAGE(production!C9,production!E9,production!G9,production!I9),"N/A") -> 175.5 | D9: =IFERROR(AVERAGE(production!D9,production!F9,production!H9,production!J9),"N/A") -> 311.5 | E9: =IFERROR(AVERAGE(production!K9,production!M9,production!O9,production!Q9),"N/A") -> 181.25 | F9: =IFERROR(AVERAGE(production!L9,production!N9,production!P9,production!R9),"N/A") -> 327.5 | G9: =IFERROR(IF(AND(ISNUMBER(C9),ISNUMBER(E9)),(E9-C9)/C9,"N/A"),"N/A") -> 0.032763533 | H9: =IFERROR(IF(AND(ISNUMBER(D9),ISNUMBER(F9)),(F9-D9)/D9,"N/A"),"N/A") -> 0.051364366 | I9: =IFERROR(SUM(financials!C9,financials!E9,financials!G9,financials!I9),"N/A") -> 1690 | J9: =IFERROR(SUM(financials!D9,financials!F9,financials!H9,financials!J9),"N/A") -> 970 | K9: =IFERROR(SUM(financials!K9,financials!M9,financials!O9,financials!Q9),"N/A") -> 1620 | L9: =IFERROR(SUM(financials!L9,financials!N9,financials!P9,financials!R9),"N/A") -> 1280 | M9: =IFERROR(IF(AND(ISNUMBER(C9),ISNUMBER(D9),I9>0),((C9+D9/6)*365)/I9,"N/A"),"N/A") -> 49.116617 | N9: =IFERROR(IF(AND(ISNUMBER(E9),ISNUMBER(F9),K9>0),((E9+F9/6)*365)/K9,"N/A"),"N/A") -> 53.135288 | O9: =IFERROR(IF(AND(ISNUMBER(J9),ISNUMBER(L9),J9<>0),(L9-J9)/ABS(J9),"N/A"),"N/A") -> 0.31958763 | P9: =IFERROR(IF(AND(ISNUMBER(L9),ISNUMBER(K9),K9<>0),L9/K9,"N/A"),"N/A") -> 0.79012346
A10: 7 | B10: ConocoPhillips | C10: =IFERROR(AVERAGE(production!C10,production!E10,production!G10,production!I10),"N/A") -> 605 | D10: =IFERROR(AVERAGE(production!D10,production!F10,production!H10,production!J10),"N/A") -> 1449 | E10: =IFERROR(AVERAGE(production!K10,production!M10,production!O10,production!Q10),"N/A") -> 629.25 | F10: =IFERROR(AVERAGE(production!L10,production!N10,production!P10,production!R10),"N/A") -> 1476 | G10: =IFERROR(IF(AND(ISNUMBER(C10),ISNUMBER(E10)),(E10-C10)/C10,"N/A"),"N/A") -> 0.040082645 | H10: =IFERROR(IF(AND(ISNUMBER(D10),ISNUMBER(F10)),(F10-D10)/D10,"N/A"),"N/A") -> 0.01863354 | I10: =IFERROR(SUM(financials!C10,financials!E10,financials!G10,financials!I10),"N/A") -> 10800 | J10: =IFERROR(SUM(financials!D10,financials!F10,financials!H10,financials!J10),"N/A") -> 11800 | K10: =IFERROR(SUM(financials!K10,financials!M10,financials!O10,financials!Q10),"N/A") -> 15100 | L10: =IFERROR(SUM(financials!L10,financials!N10,financials!P10,financials!R10),"N/A") -> 10600 | M10: =IFERROR(IF(AND(ISNUMBER(C10),ISNUMBER(D10),I10>0),((C10+D10/6)*365)/I10,"N/A"),"N/A") -> 28.608565 | N10: =IFERROR(IF(AND(ISNUMBER(E10),ISNUMBER(F10),K10>0),((E10+F10/6)*365)/K10,"N/A"),"N/A") -> 21.156705 | O10: =IFERROR(IF(AND(ISNUMBER(J10),ISNUMBER(L10),J10<>0),(L10-J10)/ABS(J10),"N/A"),"N/A") -> -0.10169492 | P10: =IFERROR(IF(AND(ISNUMBER(L10),ISNUMBER(K10),K10<>0),L10/K10,"N/A"),"N/A") -> 0.70198675
A11: 8 | B11: Coterra Energy | C11: =IFERROR(AVERAGE(production!C11,production!E11,production!G11,production!I11),"N/A") -> 98.5 | D11: =IFERROR(AVERAGE(production!D11,production!F11,production!H11,production!J11),"N/A") -> 2090 | E11: =IFERROR(AVERAGE(production!K11,production!M11,production!O11,production!Q11),"N/A") -> 105.5 | F11: =IFERROR(AVERAGE(production!L11,production!N11,production!P11,production!R11),"N/A") -> 2027.5 | G11: =IFERROR(IF(AND(ISNUMBER(C11),ISNUMBER(E11)),(E11-C11)/C11,"N/A"),"N/A") -> 0.07106599 | H11: =IFERROR(IF(AND(ISNUMBER(D11),ISNUMBER(F11)),(F11-D11)/D11,"N/A"),"N/A") -> -0.029904306 | I11: =IFERROR(SUM(financials!C11,financials!E11,financials!G11,financials!I11),"N/A") -> 1840 | J11: =IFERROR(SUM(financials!D11,financials!F11,financials!H11,financials!J11),"N/A") -> 1430 | K11: =IFERROR(SUM(financials!K11,financials!M11,financials!O11,financials!Q11),"N/A") -> 1520 | L11: =IFERROR(SUM(financials!L11,financials!N11,financials!P11,financials!R11),"N/A") -> 1430 | M11: =IFERROR(IF(AND(ISNUMBER(C11),ISNUMBER(D11),I11>0),((C11+D11/6)*365)/I11,"N/A"),"N/A") -> 88.638134 | N11: =IFERROR(IF(AND(ISNUMBER(E11),ISNUMBER(F11),K11>0),((E11+F11/6)*365)/K11,"N/A"),"N/A") -> 106.47834 | O11: =IFERROR(IF(AND(ISNUMBER(J11),ISNUMBER(L11),J11<>0),(L11-J11)/ABS(J11),"N/A"),"N/A") -> 0 | P11: =IFERROR(IF(AND(ISNUMBER(L11),ISNUMBER(K11),K11<>0),L11/K11,"N/A"),"N/A") -> 0.94078947
A12: 9 | B12: Devon Energy | C12: =IFERROR(AVERAGE(production!C12,production!E12,production!G12,production!I12),"N/A") -> 316.75 | D12: =IFERROR(AVERAGE(production!D12,production!F12,production!H12,production!J12),"N/A") -> 989.5 | E12: =IFERROR(AVERAGE(production!K12,production!M12,production!O12,production!Q12),"N/A") -> 331.5 | F12: =IFERROR(AVERAGE(production!L12,production!N12,production!P12,production!R12),"N/A") -> 1001.25 | G12: =IFERROR(IF(AND(ISNUMBER(C12),ISNUMBER(E12)),(E12-C12)/C12,"N/A"),"N/A") -> 0.046566693 | H12: =IFERROR(IF(AND(ISNUMBER(D12),ISNUMBER(F12)),(F12-D12)/D12,"N/A"),"N/A") -> 0.011874684 | I12: =IFERROR(SUM(financials!C12,financials!E12,financials!G12,financials!I12),"N/A") -> 3400 | J12: =IFERROR(SUM(financials!D12,financials!F12,financials!H12,financials!J12),"N/A") -> 3160 | K12: =IFERROR(SUM(financials!K12,financials!M12,financials!O12,financials!Q12),"N/A") -> 3350 | L12: =IFERROR(SUM(financials!L12,financials!N12,financials!P12,financials!R12),"N/A") -> 3090 | M12: =IFERROR(IF(AND(ISNUMBER(C12),ISNUMBER(D12),I12>0),((C12+D12/6)*365)/I12,"N/A"),"N/A") -> 51.708333 | N12: =IFERROR(IF(AND(ISNUMBER(E12),ISNUMBER(F12),K12>0),((E12+F12/6)*365)/K12,"N/A"),"N/A") -> 54.30056 | O12: =IFERROR(IF(AND(ISNUMBER(J12),ISNUMBER(L12),J12<>0),(L12-J12)/ABS(J12),"N/A"),"N/A") -> -0.022151899 | P12: =IFERROR(IF(AND(ISNUMBER(L12),ISNUMBER(K12),K12<>0),L12/K12,"N/A"),"N/A") -> 0.92238806
A13: 10 | B13: Diamondback Energy | C13: =IFERROR(AVERAGE(production!C13,production!E13,production!G13,production!I13),"N/A") -> 257.5 | D13: =IFERROR(AVERAGE(production!D13,production!F13,production!H13,production!J13),"N/A") -> 860.5 | E13: =IFERROR(AVERAGE(production!K13,production!M13,production!O13,production!Q13),"N/A") -> 295.75 | F13: =IFERROR(AVERAGE(production!L13,production!N13,production!P13,production!R13),"N/A") -> 995 | G13: =IFERROR(IF(AND(ISNUMBER(C13),ISNUMBER(E13)),(E13-C13)/C13,"N/A"),"N/A") -> 0.14854369 | H13: =IFERROR(IF(AND(ISNUMBER(D13),ISNUMBER(F13)),(F13-D13)/D13,"N/A"),"N/A") -> 0.15630447 | I13: =IFERROR(SUM(financials!C13,financials!E13,financials!G13,financials!I13),"N/A") -> 2900 | J13: =IFERROR(SUM(financials!D13,financials!F13,financials!H13,financials!J13),"N/A") -> 2680 | K13: =IFERROR(SUM(financials!K13,financials!M13,financials!O13,financials!Q13),"N/A") -> 3370 | L13: =IFERROR(SUM(financials!L13,financials!N13,financials!P13,financials!R13),"N/A") -> 3330 | M13: =IFERROR(IF(AND(ISNUMBER(C13),ISNUMBER(D13),I13>0),((C13+D13/6)*365)/I13,"N/A"),"N/A") -> 50.460201 | N13: =IFERROR(IF(AND(ISNUMBER(E13),ISNUMBER(F13),K13>0),((E13+F13/6)*365)/K13,"N/A"),"N/A") -> 49.993447 | O13: =IFERROR(IF(AND(ISNUMBER(J13),ISNUMBER(L13),J13<>0),(L13-J13)/ABS(J13),"N/A"),"N/A") -> 0.24253731 | P13: =IFERROR(IF(AND(ISNUMBER(L13),ISNUMBER(K13),K13<>0),L13/K13,"N/A"),"N/A") -> 0.98813056
A14: 11 | B14: EOG Resources | C14: =IFERROR(AVERAGE(production!C14,production!E14,production!G14,production!I14),"N/A") -> 480.25 | D14: =IFERROR(AVERAGE(production!D14,production!F14,production!H14,production!J14),"N/A") -> 1402.75 | E14: =IFERROR(AVERAGE(production!K14,production!M14,production!O14,production!Q14),"N/A") -> 508.25 | F14: =IFERROR(AVERAGE(production!L14,production!N14,production!P14,production!R14),"N/A") -> 1466.25 | G14: =IFERROR(IF(AND(ISNUMBER(C14),ISNUMBER(E14)),(E14-C14)/C14,"N/A"),"N/A") -> 0.058302967 | H14: =IFERROR(IF(AND(ISNUMBER(D14),ISNUMBER(F14)),(F14-D14)/D14,"N/A"),"N/A") -> 0.045268223 | I14: =IFERROR(SUM(financials!C14,financials!E14,financials!G14,financials!I14),"N/A") -> 5990 | J14: =IFERROR(SUM(financials!D14,financials!F14,financials!H14,financials!J14),"N/A") -> 6900 | K14: =IFERROR(SUM(financials!K14,financials!M14,financials!O14,financials!Q14),"N/A") -> 6110 | L14: =IFERROR(SUM(financials!L14,financials!N14,financials!P14,financials!R14),"N/A") -> 7450 | M14: =IFERROR(IF(AND(ISNUMBER(C14),ISNUMBER(D14),I14>0),((C14+D14/6)*365)/I14,"N/A"),"N/A") -> 43.510051 | N14: =IFERROR(IF(AND(ISNUMBER(E14),ISNUMBER(F14),K14>0),((E14+F14/6)*365)/K14,"N/A"),"N/A") -> 44.960413 | O14: =IFERROR(IF(AND(ISNUMBER(J14),ISNUMBER(L14),J14<>0),(L14-J14)/ABS(J14),"N/A"),"N/A") -> 0.079710145 | P14: =IFERROR(IF(AND(ISNUMBER(L14),ISNUMBER(K14),K14<>0),L14/K14,"N/A"),"N/A") -> 1.2193126
A15: 12 | B15: EQT Corporation | C15: =IFERROR(AVERAGE(production!C15,production!E15,production!G15,production!I15),"N/A") -> N/A | D15: =IFERROR(AVERAGE(production!D15,production!F15,production!H15,production!J15),"N/A") -> 5287.5 | E15: =IFERROR(AVERAGE(production!K15,production!M15,production!O15,production!Q15),"N/A") -> N/A | F15: =IFERROR(AVERAGE(production!L15,production!N15,production!P15,production!R15),"N/A") -> 5767.5 | G15: =IFERROR(IF(AND(ISNUMBER(C15),ISNUMBER(E15)),(E15-C15)/C15,"N/A"),"N/A") -> N/A | H15: =IFERROR(IF(AND(ISNUMBER(D15),ISNUMBER(F15)),(F15-D15)/D15,"N/A"),"N/A") -> 0.090780142 | I15: =IFERROR(SUM(financials!C15,financials!E15,financials!G15,financials!I15),"N/A") -> 1640 | J15: =IFERROR(SUM(financials!D15,financials!F15,financials!H15,financials!J15),"N/A") -> 2540 | K15: =IFERROR(SUM(financials!K15,financials!M15,financials!O15,financials!Q15),"N/A") -> 3590 | L15: =IFERROR(SUM(financials!L15,financials!N15,financials!P15,financials!R15),"N/A") -> 2580 | M15: =IFERROR(IF(AND(ISNUMBER(C15),ISNUMBER(D15),I15>0),((C15+D15/6)*365)/I15,"N/A"),"N/A") -> N/A | N15: =IFERROR(IF(AND(ISNUMBER(E15),ISNUMBER(F15),K15>0),((E15+F15/6)*365)/K15,"N/A"),"N/A") -> N/A | O15: =IFERROR(IF(AND(ISNUMBER(J15),ISNUMBER(L15),J15<>0),(L15-J15)/ABS(J15),"N/A"),"N/A") -> 0.015748031 | P15: =IFERROR(IF(AND(ISNUMBER(L15),ISNUMBER(K15),K15<>0),L15/K15,"N/A"),"N/A") -> 0.71866295
... A22: 19 | B22: Permian Resources | C22: =IFERROR(AVERAGE(production!C22,production!E22,production!G22,production!I22),"N/A") -> 122.5 | D22: =IFERROR(AVERAGE(production!D22,production!F22,production!H22,production!J22),"N/A") -> 367.5 | E22: =IFERROR(AVERAGE(production!K22,production!M22,production!O22,production!Q22),"N/A") -> 170.75 | F22: =IFERROR(AVERAGE(production!L22,production!N22,production!P22,production!R22),"N/A") -> 504.25 | G22: =IFERROR(IF(AND(ISNUMBER(C22),ISNUMBER(E22)),(E22-C22)/C22,"N/A"),"N/A") -> 0.39387755 | H22: =IFERROR(IF(AND(ISNUMBER(D22),ISNUMBER(F22)),(F22-D22)/D22,"N/A"),"N/A") -> 0.37210884 | I22: =IFERROR(SUM(financials!C22,financials!E22,financials!G22,financials!I22),"N/A") -> 1830 | J22: =IFERROR(SUM(financials!D22,financials!F22,financials!H22,financials!J22),"N/A") -> 660 | K22: =IFERROR(SUM(financials!K22,financials!M22,financials!O22,financials!Q22),"N/A") -> 1990 | L22: =IFERROR(SUM(financials!L22,financials!N22,financials!P22,financials!R22),"N/A") -> 1320 | M22: =IFERROR(IF(AND(ISNUMBER(C22),ISNUMBER(D22),I22>0),((C22+D22/6)*365)/I22,"N/A"),"N/A") -> 36.64959 | N22: =IFERROR(IF(AND(ISNUMBER(E22),ISNUMBER(F22),K22>0),((E22+F22/6)*365)/K22,"N/A"),"N/A") -> 46.733145 | O22: =IFERROR(IF(AND(ISNUMBER(J22),ISNUMBER(L22),J22<>0),(L22-J22)/ABS(J22),"N/A"),"N/A") -> 1 | P22: =IFERROR(IF(AND(ISNUMBER(L22),ISNUMBER(K22),K22<>0),L22/K22,"N/A"),"N/A") -> 0.66331658

Sheet data_sources
A1: DATA SOURCES & METHODOLOGY NOTES
A2: company | B2: data_type | C2: source | D2: sec_url_base | E2: notes
A3: All U.S. companies | B3: Production + Financials | C3: SEC EDGAR 8-K / Exhibit 99.1 | D3: https://www.sec.gov/cgi-bin/browse-edgar | E3: Quarterly earnings press releases filed as 8-K
A4: Antero Resources | B4: Production | C4: SEC EDGAR | D4: https://www.sec.gov/cgi-bin/browse-edgar?action=getcompany&CIK=AR | E4: Gas reported as MMcfe/d; oil extracted from liquids breakout
A5: BKV Corporation | B5: Production | C5: SEC EDGAR / IR website | D5: https://ir.bkv.com | E5: IPO'd Sep 2024; 2023 data from private filings. Gas ~79% of MMcfe/d
A6: Canadian Natural Resources | B6: Production | C6: SEDAR+ / CNR IR | D6: https://www.cnrl.com/investors | E6: Reporting in CAD$; production in bbl/d BOE
A7: Cenovus Energy | B7: Production | C7: SEC EDGAR / SEDAR+ | D7: https://www.sec.gov/cgi-bin/browse-edgar?action=getcompany&CIK=CVE | E7: Upstream only; excludes downstream/refining
A8: Chevron | B8: Production | C8: SEC EDGAR | D8: https://www.sec.gov/cgi-bin/browse-edgar?action=getcompany&CIK=CVX | E8: Worldwide production; liquids + gas
A9: Chord Energy | B9: Production | C9: SEC EDGAR | D9: https://www.sec.gov/cgi-bin/browse-edgar?action=getcompany&CIK=CHRD | E9: Formed from Oasis+Whiting merger 2022
A10: ConocoPhillips | B10: Production | C10: SEC EDGAR | D10: https://www.sec.gov/cgi-bin/browse-edgar?action=getcompany&CIK=COP | E10: Total company; includes international
A11: Coterra Energy | B11: Production | C11: SEC EDGAR | D11: https://www.sec.gov/cgi-bin/browse-edgar?action=getcompany&CIK=CTRA | E11: Permian oil + Marcellus/Anadarko gas
A12: Devon Energy | B12: Production | C12: SEC EDGAR | D12: https://www.sec.gov/cgi-bin/browse-edgar?action=getcompany&CIK=DVN | E12: Delaware Basin dominant; also Anadarko, Eagle Ford
A13: Diamondback Energy | B13: Production | C13: SEC EDGAR | D13: https://www.sec.gov/cgi-bin/browse-edgar?action=getcompany&CIK=FANG | E13: Permian only; acquired Endeavor 2024
... A25: UNIT CONVENTIONS | B25: — | C25: Industry standard | D25: — | E25: Oil: MBbl/d = thousands barrels/day | Gas: MMcf/d = millions cu ft/day | BOE conversion: 6 Mcf = 1 BOE
